{
  "vehiculos": [
    {
      "id": 2,
      "marca": "Ford",
      "modelo": "Fiesta",
      "anio": 2019,
      "color": "Rojo",
      "kilometraje": 30000,
      "transmision": "Manual",
      "precio": 12000,
      "combustible": "Gasolina"
    },
    {
      "id": 3,
      "marca": "Volkswagen",
      "modelo": "Golf",
      "anio": 2020,
      "color": "Negro",
      "kilometraje": 22000,
      "transmision": "Automática",
      "precio": 20000,
      "combustible": "Diésel"
    },
    {
      "id": 4,
      "marca": "Tesla",
      "modelo": "Model 3",
      "anio": 2022,
      "color": "Azul",
      "kilometraje": 5000,
      "transmision": "Automática",
      "precio": 35000,
      "combustible": "Eléctrico"
    },
    {
      "id": 5,
      "marca": "BMW",
      "modelo": "Serie 3",
      "anio": 2018,
      "color": "Gris",
      "kilometraje": 45000,
      "transmision": "Automática",
      "precio": 25000,
      "combustible": "Gasolina"
    },
    {
      "id": 6,
      "marca": "Audi",
      "modelo": "A4",
      "anio": 2019,
      "color": "Blanco",
      "kilometraje": 32000,
      "transmision": "Automática",
      "precio": 27000,
      "combustible": "Gasolina"
    },
    {
      "id": 7,
      "marca": "Mercedes-Benz",
      "modelo": "Clase C",
      "anio": 2020,
      "color": "Plata",
      "kilometraje": 18000,
      "transmision": "Automática",
      "precio": 30000,
      "combustible": "Diésel"
    },
    {
      "id": 8,
      "marca": "Hyundai",
      "modelo": "Tucson",
      "anio": 2021,
      "color": "Verde",
      "kilometraje": 10000,
      "transmision": "Automática",
      "precio": 22000,
      "combustible": "Gasolina"
    },
    {
      "id": 9,
      "marca": "Nissan",
      "modelo": "Qashqai",
      "anio": 2020,
      "color": "Naranja",
      "kilometraje": 25000,
      "transmision": "Manual",
      "precio": 19000,
      "combustible": "Gasolina"
    },
    {
      "id": 10,
      "marca": "Renault",
      "modelo": "Clio",
      "anio": 2017,
      "color": "Amarillo",
      "kilometraje": 50000,
      "transmision": "Manual",
      "precio": 11000,
      "combustible": "Gasolina"
    }
  ],
  "usuarios": []
}